pylipd/__init__.py
pylipd/lipd.py
pylipd/lipd_series.py
pylipd/usage.py
pylipd/usage_parallel.py
pylipd/classes/__init__.py
pylipd/classes/archivetype.py
pylipd/classes/calibration.py
pylipd/classes/change.py
pylipd/classes/changelog.py
pylipd/classes/chrondata.py
pylipd/classes/compilation.py
pylipd/classes/dataset.py
pylipd/classes/datatable.py
pylipd/classes/funding.py
pylipd/classes/interpretation.py
pylipd/classes/interpretationseasonality.py
pylipd/classes/interpretationvariable.py
pylipd/classes/location.py
pylipd/classes/model.py
pylipd/classes/paleodata.py
pylipd/classes/paleoproxy.py
pylipd/classes/paleoproxygeneral.py
pylipd/classes/paleounit.py
pylipd/classes/paleovariable.py
pylipd/classes/person.py
pylipd/classes/physicalsample.py
pylipd/classes/publication.py
pylipd/classes/resolution.py
pylipd/classes/uncertainty.py
pylipd/classes/variable.py
pylipd/classes/templates/datatable.py
pylipd/data/ODP846.Lawrence.2006.lpd
pylipd/data/Pages2k/Ant-WAIS-Divide.Severinghaus.2012.lpd
pylipd/data/Pages2k/Arc-Kongressvatnet.D'Andrea.2012.lpd
pylipd/data/Pages2k/Asi-SourthAndMiddleUrals.Demezhko.2007.lpd
pylipd/data/Pages2k/Eur-CoastofPortugal.Abrantes.2011.lpd
pylipd/data/Pages2k/Eur-FinnishLakelands.Helama.2014.lpd
pylipd/data/Pages2k/Eur-LakeSilvaplana.Trachsel.2010.lpd
pylipd/data/Pages2k/Eur-NorthernScandinavia.Esper.2012.lpd
pylipd/data/Pages2k/Eur-NorthernSpain.Martin-Chivelet.2011.lpd
pylipd/data/Pages2k/Eur-SpanishPyrenees.Dorado-Linan.2012.lpd
pylipd/data/Pages2k/Eur-SpannagelCave.Mangini.2005.lpd
pylipd/data/Pages2k/Eur-Stockholm.Leijonhufvud.2009.lpd
pylipd/data/Pages2k/Ocn-AlboranSea436B.Nieto-Moreno.2013.lpd
pylipd/data/Pages2k/Ocn-FeniDrift.Richter.2009.lpd
pylipd/data/Pages2k/Ocn-PedradeLume-CapeVerdeIslands.Moses.2006.lpd
pylipd/data/Pages2k/Ocn-RedSea.Felis.2000.lpd
"pylipd/data/Pages2k/Ocn-SinaiPeninsula,RedSea.Moustafa.2000.lpd"
pylipd/data/Temp12k/ElGygytgynCrater.Schwamborn.2006.lpd
pylipd/data/Temp12k/MD03-2601.Kim.2012.lpd
pylipd-1.5.2.dist-info/METADATA
pylipd-1.5.2.dist-info/WHEEL
pylipd-1.5.2.dist-info/top_level.txt
pylipd-1.5.2.dist-info/RECORD
