Metadata-Version: 2.4
Name: pylipd
Version: 1.5.2
Summary: Python utilities for handling LiPD data
Author: Deborah Khider
Author-email: Varun Ratnakar <varunratnakar@gmail.com>
License: Apache-2.0
Project-URL: Homepage, https://github.com/linkedearth/pylipd
Project-URL: Issues, https://github.com/linkedearth/pylipd/issues
Requires-Python: >=3.11
Requires-Dist: rdflib
Requires-Dist: pandas
Requires-Dist: doi2bib
Requires-Dist: pybtex
Requires-Dist: tqdm
Requires-Dist: bagit
Requires-Dist: numpy
Requires-Dist: bibtexparser
Requires-Dist: beautifulsoup4
Requires-Dist: requests
